search_youtube_url.py
search_youtube_url-1.0.3.dist-info/METADATA
search_youtube_url-1.0.3.dist-info/WHEEL
search_youtube_url-1.0.3.dist-info/entry_points.txt
search_youtube_url-1.0.3.dist-info/top_level.txt
search_youtube_url-1.0.3.dist-info/RECORD
