Metadata-Version: 2.1
Name: search-youtube-url
Version: 1.0.3
Summary: UNKNOWN
Home-page: UNKNOWN
License: UNKNOWN
Platform: UNKNOWN
Requires-Dist: google-api-python-client
Requires-Dist: python-dotenv
